{
	"extends": ["@repo/biome/base"],
	"overrides": [
		{
			"include": [
				"**/__tests__/**",
				"**/*.spec.ts",
				"**/*.spec.tsx",
				"**/*.test.ts",
				"**/*.test.tsx"
			],
			"linter": {
				"rules": {
					"style": {
						"noNonNullAssertion": "off"
					}
				}
			}
		},
		{
			"include": [
				"packages/client/ui/src/components/atoms/slider.tsx",
				"packages/client/ui/src/components/atoms/step-indicator.tsx"
			],
			"linter": {
				"rules": {
					"suspicious": {
						"noArrayIndexKey": "off"
					}
				}
			}
		},
		{
			"include": ["packages/client/ui/src/components/atoms/chart.tsx"],
			"linter": {
				"rules": {
					"security": {
						"noDangerouslySetInnerHtml": "off"
					}
				}
			}
		}
	],
	"files": {
		"ignore": [
			"dist",
			"**/dist",
			".next",
			"**/.next",
			".source",
			"**/.source",
			"playwright-report",
			"**/playwright-report",
			"test-results",
			"**/test-results"
		]
	}
}
